Metadata-Version: 2.1
Name: gym-embedding-world
Version: 0.0.4.0
Summary: Two word embedding mapping compatible with OpenAI gym.
Home-page: https://github.com/SamirMoustafa/gym-embedding-world/
Author: Samir Moustafa
Author-email: samir.moustafa.97@gmail.com
License: MIT
Keywords: embedding_world
Platform: UNKNOWN
Classifier: Operating System :: OS Independent
Classifier: Programming Language :: Python :: 3 
Classifier: Programming Language :: Python :: 3.5
Classifier: Programming Language :: Python :: 3.6
Requires-Python: >=3.5,<3.7
